mistralclient/__init__.py
mistralclient/exceptions.py
mistralclient/i18n.py
mistralclient/shell.py
mistralclient/utils.py
mistralclient/api/__init__.py
mistralclient/api/base.py
mistralclient/api/client.py
mistralclient/api/httpclient.py
mistralclient/api/releasenotes/notes/fix-cli-error-messages-2f59329557a5734f.yaml
mistralclient/api/v2/__init__.py
mistralclient/api/v2/action_executions.py
mistralclient/api/v2/actions.py
mistralclient/api/v2/client.py
mistralclient/api/v2/code_sources.py
mistralclient/api/v2/cron_triggers.py
mistralclient/api/v2/dynamic_actions.py
mistralclient/api/v2/environments.py
mistralclient/api/v2/event_triggers.py
mistralclient/api/v2/executions.py
mistralclient/api/v2/members.py
mistralclient/api/v2/tasks.py
mistralclient/api/v2/workbooks.py
mistralclient/api/v2/workflows.py
mistralclient/auth/__init__.py
mistralclient/auth/auth_types.py
mistralclient/auth/keycloak.py
mistralclient/auth/keystone.py
mistralclient/commands/__init__.py
mistralclient/commands/v2/__init__.py
mistralclient/commands/v2/action_executions.py
mistralclient/commands/v2/actions.py
mistralclient/commands/v2/base.py
mistralclient/commands/v2/code_sources.py
mistralclient/commands/v2/cron_triggers.py
mistralclient/commands/v2/dynamic_actions.py
mistralclient/commands/v2/environments.py
mistralclient/commands/v2/event_triggers.py
mistralclient/commands/v2/executions.py
mistralclient/commands/v2/members.py
mistralclient/commands/v2/tasks.py
mistralclient/commands/v2/workbooks.py
mistralclient/commands/v2/workflows.py
mistralclient/osc/__init__.py
mistralclient/osc/plugin.py
mistralclient/tests/__init__.py
mistralclient/tests/functional/__init__.py
mistralclient/tests/functional/cli/__init__.py
mistralclient/tests/functional/cli/base.py
mistralclient/tests/functional/cli/v2/__init__.py
mistralclient/tests/functional/cli/v2/base_v2.py
mistralclient/tests/functional/cli/v2/test_cli_multi_tenancy.py
mistralclient/tests/functional/cli/v2/test_cli_v2.py
python_mistralclient-6.1.0.dist-info/AUTHORS
python_mistralclient-6.1.0.dist-info/LICENSE
python_mistralclient-6.1.0.dist-info/METADATA
python_mistralclient-6.1.0.dist-info/WHEEL
python_mistralclient-6.1.0.dist-info/entry_points.txt
python_mistralclient-6.1.0.dist-info/pbr.json
python_mistralclient-6.1.0.dist-info/top_level.txt
python_mistralclient-6.1.0.dist-info/RECORD
