Metadata-Version: 2.1
Name: python-mistralclient
Version: 6.1.0
Summary: Mistral Client Library
Home-page: https://docs.openstack.org/python-mistralclient/latest/
Author: OpenStack
Author-email: openstack-discuss@lists.openstack.org
License: Apache Software License
Classifier: Programming Language :: Python
Classifier: Programming Language :: Python :: Implementation :: CPython
Classifier: Programming Language :: Python :: 3 :: Only
Classifier: Programming Language :: Python :: 3
Classifier: Programming Language :: Python :: 3.9
Classifier: Programming Language :: Python :: 3.10
Classifier: Programming Language :: Python :: 3.11
Classifier: Environment :: OpenStack
Classifier: Intended Audience :: Information Technology
Classifier: Intended Audience :: System Administrators
Classifier: License :: OSI Approved :: Apache Software License
Classifier: Operating System :: POSIX :: Linux
Requires-Python: >=3.9
License-File: LICENSE
Requires-Dist: cliff!=2.9.0,>=2.8.0
Requires-Dist: osc-lib>=1.8.0
Requires-Dist: oslo.utils>=3.33.0
Requires-Dist: oslo.i18n>=3.15.3
Requires-Dist: oslo.serialization!=2.19.1,>=2.18.0
Requires-Dist: pbr!=2.1.0,>=2.0.0
Requires-Dist: keystoneauth1>=3.4.0
Requires-Dist: PyYAML>=3.13
Requires-Dist: requests>=2.14.2
Requires-Dist: stevedore>=1.20.0
